[
  {
    "Type": "DCDungeonLayoutDataAsset",
    "Name": "Id_DungeonLayout_Crypt_4x4_16",
    "Class": "UScriptClass'DCDungeonLayoutDataAsset'",
    "Flags": "RF_Public | RF_Standalone | RF_WasLoaded | RF_LoadCompleted",
    "Properties": {
      "Size": {
        "X": 4,
        "Y": 4
      },
      "SlotTypes": [
        "EDCDungeonLayoutSlotType::Boss",
        "EDCDungeonLayoutSlotType::Altar",
        "EDCDungeonLayoutSlotType::Down",
        "EDCDungeonLayoutSlotType::Escape",
        "EDCDungeonLayoutSlotType::Down",
        "EDCDungeonLayoutSlotType::Key",
        "EDCDungeonLayoutSlotType::None",
        "EDCDungeonLayoutSlotType::Escape",
        "EDCDungeonLayoutSlotType::Altar",
        "EDCDungeonLayoutSlotType::None",
        "EDCDungeonLayoutSlotType::None",
        "EDCDungeonLayoutSlotType::Down",
        "EDCDungeonLayoutSlotType::Escape",
        "EDCDungeonLayoutSlotType::Down",
        "EDCDungeonLayoutSlotType::Escape",
        "EDCDungeonLayoutSlotType::Escape"
      ]
    }
  }
]